magic_thumbnail/__init__.py
magic_thumbnail/creator.py
tests/__init__.py
tests/test_creator.py
magic_thumbnail-0.1.0.dist-info/LICENSE
magic_thumbnail-0.1.0.dist-info/METADATA
magic_thumbnail-0.1.0.dist-info/WHEEL
magic_thumbnail-0.1.0.dist-info/top_level.txt
magic_thumbnail-0.1.0.dist-info/RECORD
