Metadata-Version: 2.2
Name: magic_thumbnail
Version: 0.1.0
Summary: A Python library to generate multiple thumbnails from high-resolution images.
Home-page: https://github.com/aths7/magic_thumbnail
Author: Atharva Wankhede
Author-email: Atharva Wankhede <atharvaw007@gmail.com>
License: MIT
Classifier: Programming Language :: Python :: 3
Classifier: License :: OSI Approved :: MIT License
Classifier: Operating System :: OS Independent
Requires-Python: >=3.6
License-File: LICENSE
Requires-Dist: Pillow>=10.0.0
Requires-Dist: requests>=2.0.0
Requires-Dist: python-dotenv>=0.19.0
Dynamic: author
Dynamic: home-page
Dynamic: requires-python
